datascroller/__init__.py
datascroller/command_line.py
datascroller/demo.py
datascroller/help_screen.py
datascroller/keybindings.py
datascroller/scroller.py
datascroller/demo_data/titanic.csv
datascroller/demo_data/titanic_pipe.csv
datascroller/demo_data/titanic_utf16.csv
datascroller-1.3.2.dist-info/METADATA
datascroller-1.3.2.dist-info/RECORD
datascroller-1.3.2.dist-info/WHEEL
datascroller-1.3.2.dist-info/entry_points.txt
datascroller-1.3.2.dist-info/top_level.txt
